aioworkers_sentry/__init__.py
aioworkers_sentry/client.py
aioworkers_sentry/sentry.ini
aioworkers_sentry-0.6.dist-info/METADATA
aioworkers_sentry-0.6.dist-info/WHEEL
aioworkers_sentry-0.6.dist-info/entry_points.txt
aioworkers_sentry-0.6.dist-info/licenses/LICENSE
aioworkers_sentry-0.6.dist-info/RECORD
